<?xml version='1.0' encoding='utf-8' standalone='yes' ?>
<map>
    <string name="flutter.speciesCaughtName">VGhpcyBpcyB0aGUgcHJlZml4IGZvciBhIGxpc3Qu![&quot;Slipshadow&quot;,&quot;False Rat&quot;,&quot;Fallowfern&quot;,&quot;Wiggleneck&quot;]</string>
    <string name="flutter.locs">VGhpcyBpcyB0aGUgcHJlZml4IGZvciBhIGxpc3Qu![&quot;[{\&quot;lat\&quot;:38.9834526,\&quot;lon\&quot;:-76.9414681},{\&quot;lat\&quot;:38.9890705,\&quot;lon\&quot;:-76.9358486}]&quot;,&quot;[{\&quot;lat\&quot;:38.9901988,\&quot;lon\&quot;:-76.9359862}]&quot;,&quot;[{\&quot;lat\&quot;:38.989787,\&quot;lon\&quot;:-76.935923}]&quot;,&quot;[{\&quot;lat\&quot;:38.9894511,\&quot;lon\&quot;:-76.9364147}]&quot;]</string>
    <string name="flutter.userID">cbe92997-5150-4469-95bc-c61cf53f7099</string>
    <string name="flutter.allCaught">VGhpcyBpcyB0aGUgcHJlZml4IGZvciBhIGxpc3Qu![&quot;{\&quot;name\&quot;:\&quot;Slipshadow\&quot;,\&quot;description\&quot;:\&quot;Many believe the Slipshadow was named for its extraordinary stealth, but this is far from the truth. Slipshadows are extremely uncoordinated, and the snarky terpieologists who first studied them commented that they could slip on their own shadows. They eat mostly soups, particularly favoring tomato-based soups, and consequently tend to have very high cleaning bills.\&quot;,\&quot;thumbnail\&quot;:\&quot;89a186cc979842d7a91fe62082ce0200\&quot;,\&quot;image\&quot;:\&quot;b71fc6768e8d4b54891162245f44a950\&quot;,\&quot;stats\&quot;:{\&quot;Avuncularity\&quot;:6,\&quot;Destrucity\&quot;:9,\&quot;Panache\&quot;:5,\&quot;Spiciness\&quot;:5}}&quot;,&quot;{\&quot;name\&quot;:\&quot;False Rat\&quot;,\&quot;description\&quot;:\&quot;The False Rat looks nothing like a rat, making the name confusing to many on first encountering it. The name actually comes from their tendency to gnaw 3-inch holes in walls. They use these holes to store burritos, which they prefer slightly aged, and can often be found in the same areas as Burrowbosses.\&quot;,\&quot;thumbnail\&quot;:\&quot;d9c477b16ec64ca4a5a81603a1fa406c\&quot;,\&quot;image\&quot;:\&quot;97bbc1fa079b45e5ba9283dd3cc716d0\&quot;,\&quot;stats\&quot;:{\&quot;Avuncularity\&quot;:4,\&quot;Destrucity\&quot;:9,\&quot;Panache\&quot;:4,\&quot;Spiciness\&quot;:8}}&quot;,&quot;{\&quot;name\&quot;:\&quot;Fallowfern\&quot;,\&quot;description\&quot;:\&quot;Fallowferns are often found around the edges of unplanted agricultural fields, particularly those adjacent to wooded areas. They enjoy smoked salmon, but as this is seldom found in their native habitat they often settle for corn kernels or other grass seeds. They can be recognized by their call, which has been likened to the Bee Gees.\&quot;,\&quot;thumbnail\&quot;:\&quot;668f4cf25969487ba7e7af5f1744dfa3\&quot;,\&quot;image\&quot;:\&quot;96fdbb749f7043399d4463a1564a8ccd\&quot;,\&quot;stats\&quot;:{\&quot;Avuncularity\&quot;:6,\&quot;Destrucity\&quot;:4,\&quot;Panache\&quot;:8,\&quot;Spiciness\&quot;:7}}&quot;,&quot;{\&quot;name\&quot;:\&quot;Wiggleneck\&quot;,\&quot;description\&quot;:\&quot;The Wiggleneck has pairs of magnetic structures in it throat that allow it to safely breathe in or around plasmas. It also frequently uses these for party tricks, though these tricks almost never impress the other party-goers. Their diet consists primarily of sweet liquids, such as sugar water or cola, typically consumed through silly straws.\&quot;,\&quot;thumbnail\&quot;:\&quot;508d9483cf754827923001e9ef039781\&quot;,\&quot;image\&quot;:\&quot;ae71f4c49ea047019cfb37c86f626833\&quot;,\&quot;stats\&quot;:{\&quot;Avuncularity\&quot;:10,\&quot;Destrucity\&quot;:6,\&quot;Panache\&quot;:2,\&quot;Spiciness\&quot;:7}}&quot;]</string>
    <string name="flutter.speciesCaughtID">VGhpcyBpcyB0aGUgcHJlZml4IGZvciBhIGxpc3Qu![&quot;099fdbe454ef4c8182a29d8ac643b223&quot;,&quot;107401576b0043a4b41a01ce63f23f75&quot;,&quot;9cc50255087941e4952a3947a87e580c&quot;,&quot;f32678076ff54acb9977c8b76d7e370c&quot;]</string>
    <string name="flutter.speciesCaughtTN">VGhpcyBpcyB0aGUgcHJlZml4IGZvciBhIGxpc3Qu![&quot;/data/user/0/com.example.terpiez/app_flutter/89a186cc979842d7a91fe62082ce0200.png&quot;,&quot;/data/user/0/com.example.terpiez/app_flutter/d9c477b16ec64ca4a5a81603a1fa406c.png&quot;,&quot;/data/user/0/com.example.terpiez/app_flutter/668f4cf25969487ba7e7af5f1744dfa3.png&quot;,&quot;/data/user/0/com.example.terpiez/app_flutter/508d9483cf754827923001e9ef039781.png&quot;]</string>
    <string name="flutter.speciesCaughtIMG">VGhpcyBpcyB0aGUgcHJlZml4IGZvciBhIGxpc3Qu![&quot;/data/user/0/com.example.terpiez/app_flutter/b71fc6768e8d4b54891162245f44a950.png&quot;,&quot;/data/user/0/com.example.terpiez/app_flutter/97bbc1fa079b45e5ba9283dd3cc716d0.png&quot;,&quot;/data/user/0/com.example.terpiez/app_flutter/96fdbb749f7043399d4463a1564a8ccd.png&quot;,&quot;/data/user/0/com.example.terpiez/app_flutter/ae71f4c49ea047019cfb37c86f626833.png&quot;]</string>
    <long name="flutter.terpsCaught" value="4" />
</map>
